lyapimcp/__init__.py
lyapimcp/py.typed
lyapimcp/server.py
lyapimcp-0.1.0.dist-info/METADATA
lyapimcp-0.1.0.dist-info/WHEEL
lyapimcp-0.1.0.dist-info/entry_points.txt
lyapimcp-0.1.0.dist-info/licenses/LICENSE
lyapimcp-0.1.0.dist-info/RECORD
